Upload/Upload.py
Upload/__init__.py
flaskImgUp-0.0.1.dist-info/METADATA
flaskImgUp-0.0.1.dist-info/RECORD
flaskImgUp-0.0.1.dist-info/WHEEL
flaskImgUp-0.0.1.dist-info/top_level.txt
